django_model_scanner/__init__.py
django_model_scanner/__main__.py
django_model_scanner/ast_utils.py
django_model_scanner/checker.py
django_model_scanner/export.py
django_model_scanner/main.py
django_model_scanner/model_parser.py
django_model_scanner-0.1.0.dist-info/METADATA
django_model_scanner-0.1.0.dist-info/WHEEL
django_model_scanner-0.1.0.dist-info/entry_points.txt
django_model_scanner-0.1.0.dist-info/RECORD
