Metadata-Version: 2.4
Name: django-model-scanner
Version: 0.1.0
Summary: Static analysis tool for Django models using pylint and astroid
Requires-Python: >=3.11
Requires-Dist: astroid>=3.0.0
Requires-Dist: pylint>=4.0.4
Requires-Dist: pyyaml>=6.0
Provides-Extra: dev
Requires-Dist: django>=3.2; extra == 'dev'
Requires-Dist: pytest-cov>=4.0.0; extra == 'dev'
Requires-Dist: pytest>=7.0.0; extra == 'dev'
Provides-Extra: examples
Requires-Dist: django>=3.2; extra == 'examples'
